lib/__init__.py
lib/garvit.py
lib/harshit.py
Topsis_harshit_102103461-0.0.1.dist-info/METADATA
Topsis_harshit_102103461-0.0.1.dist-info/WHEEL
Topsis_harshit_102103461-0.0.1.dist-info/top_level.txt
Topsis_harshit_102103461-0.0.1.dist-info/RECORD
